source/__init__.py
source/analyzer.py
source/decorator.py
source/evaluator.py
source/printer.py
source/rich_printer.py
whytrace-0.1.4.dist-info/licenses/LICENSE
whytrace-0.1.4.dist-info/METADATA
whytrace-0.1.4.dist-info/WHEEL
whytrace-0.1.4.dist-info/top_level.txt
whytrace-0.1.4.dist-info/RECORD
