Metadata-Version: 2.4
Name: whytrace
Version: 0.1.4
Summary: A conditional logic visualizer for Python
Author: Hemapriya N
Project-URL: Homepage, https://github.com/Nhemapriya/whytrace
Project-URL: Repository, https://github.com/Nhemapriya/whytrace
Requires-Python: >=3.9
License-File: LICENSE
Requires-Dist: rich>=13.0
Dynamic: license-file
